mll_package/__init__.py
mll_package/__main__.py
mll_package/run.py
mll_package-1.0.1.dist-info/METADATA
mll_package-1.0.1.dist-info/WHEEL
mll_package-1.0.1.dist-info/top_level.txt
mll_package-1.0.1.dist-info/RECORD
