Metadata-Version: 2.1
Name: mll-package
Version: 1.0.1
Summary: A custom interpreter for MLL
Home-page: UNKNOWN
Author: jmnew03
Author-email: jmnew03@kaist.ac.kr
License: UNKNOWN
Platform: UNKNOWN
